{
  "id": "mock-doc-id",
  "url": null,
  "type": "project",
  "href": null,
  "tags": [],
  "first_publication_date": "1970-01-01T00:00:01+0000",
  "last_publication_date": "1970-01-01T00:00:01+0000",
  "slugs": [],
  "linked_documents": [],
  "lang": "en-us",
  "alternate_languages": [],
  "data": {
    "title": "just",
    "thumbnail": {
      "dimensions": {
        "width": 900,
        "height": 500
      },
      "alt": null,
      "copyright": null,
      "url": "https://images.unsplash.com/photo-1491975474562-1f4e30bc9468"
    },
    "shortDescription": "movement",
    "description": [
      {
        "type": "paragraph",
        "text": "Est cupidatat duis do mollit elit minim aute eiusmod pariatur irure deserunt sint duis. Duis sint quis Lorem ex. Deserunt ipsum sit mollit cupidatat voluptate nulla incididunt consectetur.",
        "spans": []
      }
    ],
    "tags": "copy",
    "sortOrder": 23,
    "slices": []
  }
}